LICENSE.txt
MANIFEST.in
README.rst
setup.py
flask_json_errorhandler/__init__.py
flask_json_errorhandler.egg-info/PKG-INFO
flask_json_errorhandler.egg-info/SOURCES.txt
flask_json_errorhandler.egg-info/dependency_links.txt
flask_json_errorhandler.egg-info/requires.txt
flask_json_errorhandler.egg-info/top_level.txt