Metadata-Version: 1.1
Name: flask-json-errorhandler
Version: 1.0.2
Summary: Register json errorhandlers for a flask REST server
Home-page: https://github.com/fischerfredl/flask-json-errorhandler
Author: Alfred Melch
Author-email: alfred.melch@gmx.de
License: MIT
Keywords: flask,json,errorhandler
Platform: UNKNOWN
Classifier: Framework :: Flask
Classifier: License :: OSI Approved :: MIT License
Classifier: Programming Language :: Python :: 2.7
Classifier: Programming Language :: Python :: 3.5
Classifier: Programming Language :: Python :: 3.6
